Metadata-Version: 2.1
Name: fastapi-route-log
Version: 0.0.6
Summary: A FastAPI route for logging every request 
Home-page: https://github.com/12345k/fastapi_logging.git
Author: karthick aravindan (12345k)
Author-email: karathickaravindan@gmail.com
License: MIT
Keywords: fastapi,logging,custom,router
Platform: UNKNOWN
Classifier: Development Status :: 5 - Production/Stable
Classifier: Environment :: Console
Classifier: Intended Audience :: Developers
Classifier: License :: OSI Approved :: MIT License
Classifier: Operating System :: OS Independent
Classifier: Programming Language :: Python
Classifier: Programming Language :: Python :: 3.6
Classifier: Programming Language :: Python :: 3.7
Classifier: Programming Language :: Python :: 3.8
Classifier: Programming Language :: Python :: 3.9
Classifier: Topic :: Software Development :: Libraries
